volcano_base/__init__.py
volcano_base/__init__.pyi
volcano_base/config.py
volcano_base/config.pyi
volcano_base/down.pyi
volcano_base/load.pyi
volcano_base/manipulate.pyi
volcano_base/down/__init__.py
volcano_base/down/__init__.pyi
volcano_base/down/cesm2.py
volcano_base/down/cesm2.pyi
volcano_base/down/historic_so2.py
volcano_base/down/historic_so2.pyi
volcano_base/down/mcg24.py
volcano_base/down/mcg24.pyi
volcano_base/down/ob16.py
volcano_base/down/ob16.pyi
volcano_base/load/__init__.py
volcano_base/load/__init__.pyi
volcano_base/load/load_c2w_files.py
volcano_base/load/load_c2w_files.pyi
volcano_base/load/load_mcg24_files.py
volcano_base/load/load_mcg24_files.pyi
volcano_base/load/load_ob16.py
volcano_base/load/load_ob16.pyi
volcano_base/manipulate/__init__.py
volcano_base/manipulate/__init__.pyi
volcano_base/manipulate/time_series.py
volcano_base/manipulate/time_series.pyi
volcano_base-2.5.0.dist-info/METADATA
volcano_base-2.5.0.dist-info/WHEEL
volcano_base-2.5.0.dist-info/licenses/LICENSE
volcano_base-2.5.0.dist-info/RECORD
