Metadata-Version: 2.4
Name: volcano-base
Version: 2.5.0
Summary: Download, find and manipulate volcano and climate related time series
Author-email: engeir <engeir@pm.me>
License-Expression: MIT
License-File: LICENSE
Requires-Python: >=3.12
Requires-Dist: beautifulsoup4>=4.12.3
Requires-Dist: cftime>=1.6.3
Requires-Dist: dask>=2024.2.0
Requires-Dist: datetime>=5.4
Requires-Dist: h5netcdf>=1.3.0
Requires-Dist: importlib-metadata<8,>=7.1.0; python_version < '3.10'
Requires-Dist: matplotlib>=3.8.3
Requires-Dist: nc-time-axis>=1.4.1
Requires-Dist: numpy>=1.26.4
Requires-Dist: pydantic>=2.6.2
Requires-Dist: requests>=2.31.0
Requires-Dist: returns>=0.22.0
Requires-Dist: rich>=13.7.0
Requires-Dist: scipy>=1.12.0
Requires-Dist: xarray>=2024.1.1
